<?xml version="1.0" encoding="utf-8"?>
<Screenshot xmlns:xsd="http://www.w3.org/2001/XMLSchema" xmlns:xsi="http://www.w3.org/2001/XMLSchema-instance">
  <Cars />
  <MyCar>
    <Position>
      <X>-1342.705</X>
      <Y>-3048.37476</Y>
      <Z>13.5632668</Z>
    </Position>
    <Rotation>
      <X>-0.192277</X>
      <Y>-0.000528467</Y>
      <Z>90.06569</Z>
    </Rotation>
    <Handle>514</Handle>
    <Bounds>
      <Vector3>
        <X>-1340.14355</X>
        <Y>-3049.393</Y>
        <Z>12.8438959</Z>
      </Vector3>
      <Vector3>
        <X>-1340.14587</X>
        <Y>-3047.35059</Y>
        <Z>12.843915</Z>
      </Vector3>
      <Vector3>
        <X>-1345.25891</X>
        <Y>-3049.399</Y>
        <Z>12.8267288</Z>
      </Vector3>
      <Vector3>
        <X>-1340.14844</X>
        <Y>-3049.39331</Y>
        <Z>14.2997856</Z>
      </Vector3>
      <Vector3>
        <X>-1345.26123</X>
        <Y>-3047.35645</Y>
        <Z>12.8267479</Z>
      </Vector3>
      <Vector3>
        <X>-1340.15076</X>
        <Y>-3047.35059</Y>
        <Z>14.2998037</Z>
      </Vector3>
      <Vector3>
        <X>-1345.26379</X>
        <Y>-3049.39917</Y>
        <Z>14.2826185</Z>
      </Vector3>
      <Vector3>
        <X>-1345.26611</X>
        <Y>-3047.35645</Y>
        <Z>14.2826376</Z>
      </Vector3>
    </Bounds>
    <CenterCamPosition>
      <X>0</X>
      <Y>0</Y>
    </CenterCamPosition>
    <ScreenBounds />
    <DistanceToCam>0</DistanceToCam>
    <Speed>2.06777525</Speed>
    <AccInput>0</AccInput>
    <RPM>0.2</RPM>
    <Gear>1</Gear>
    <SteeringAngle>-2.55502783E-21</SteeringAngle>
    <WheelSpeed>0</WheelSpeed>
    <CarType>Sports</CarType>
  </MyCar>
  <Peds />
  <Time>146814</Time>
  <LastFrameTime>0.016515905</LastFrameTime>
  <MyProperty>0</MyProperty>
  <Weather>ExtraSunny</Weather>
  <Steering>127</Steering>
  <Acc>127</Acc>
  <Brake>127</Brake>
  <DayTime>23:45:54</DayTime>
  <Position>
    <X>-1343.87378</X>
    <Y>-3048.37622</Y>
    <Z>14.4593277</Z>
  </Position>
  <Rotation>
    <X>-0.6897499</X>
    <Y>0.499474674</Y>
    <Z>90.06568</Z>
  </Rotation>
</Screenshot>