<?xml version="1.0" encoding="utf-8"?>
<Screenshot xmlns:xsd="http://www.w3.org/2001/XMLSchema" xmlns:xsi="http://www.w3.org/2001/XMLSchema-instance">
  <Cars />
  <MyCar>
    <Position>
      <X>-1368.7041</X>
      <Y>-3048.37622</Y>
      <Z>13.559824</Z>
    </Position>
    <Rotation>
      <X>0.0606012419</X>
      <Y>0.0151182143</Y>
      <Z>90.0657959</Z>
    </Rotation>
    <Handle>514</Handle>
    <Bounds>
      <Vector3>
        <X>-1366.14587</X>
        <Y>-3049.39478</Y>
        <Z>12.8294392</Z>
      </Vector3>
      <Vector3>
        <X>-1366.14819</X>
        <Y>-3047.35229</Y>
        <Z>12.8289</Z>
      </Vector3>
      <Vector3>
        <X>-1371.26135</X>
        <Y>-3049.40063</Y>
        <Z>12.83485</Z>
      </Vector3>
      <Vector3>
        <X>-1366.14429</X>
        <Y>-3049.39453</Y>
        <Z>14.2853355</Z>
      </Vector3>
      <Vector3>
        <X>-1371.26367</X>
        <Y>-3047.35815</Y>
        <Z>12.8343105</Z>
      </Vector3>
      <Vector3>
        <X>-1366.14661</X>
        <Y>-3047.35181</Y>
        <Z>14.2847967</Z>
      </Vector3>
      <Vector3>
        <X>-1371.25977</X>
        <Y>-3049.40039</Y>
        <Z>14.2907467</Z>
      </Vector3>
      <Vector3>
        <X>-1371.26208</X>
        <Y>-3047.35767</Y>
        <Z>14.2902079</Z>
      </Vector3>
    </Bounds>
    <CenterCamPosition>
      <X>0</X>
      <Y>0</Y>
    </CenterCamPosition>
    <ScreenBounds />
    <DistanceToCam>0</DistanceToCam>
    <Speed>4.32416773</Speed>
    <AccInput>0.179085016</AccInput>
    <RPM>0.239976481</RPM>
    <Gear>1</Gear>
    <SteeringAngle>0</SteeringAngle>
    <WheelSpeed>0</WheelSpeed>
    <CarType>Sports</CarType>
  </MyCar>
  <Peds />
  <Time>155381</Time>
  <LastFrameTime>0.0166003089</LastFrameTime>
  <MyProperty>0</MyProperty>
  <Weather>ExtraSunny</Weather>
  <Steering>127</Steering>
  <Acc>149</Acc>
  <Brake>127</Brake>
  <DayTime>23:50:11</DayTime>
  <Position>
    <X>-1369.83142</X>
    <Y>-3048.37744</Y>
    <Z>14.4610844</Z>
  </Position>
  <Rotation>
    <X>-0.4409273</X>
    <Y>0.514886</Y>
    <Z>90.0658</Z>
  </Rotation>
</Screenshot>