<?xml version="1.0" encoding="utf-8"?>
<Screenshot xmlns:xsd="http://www.w3.org/2001/XMLSchema" xmlns:xsi="http://www.w3.org/2001/XMLSchema-instance">
  <Cars />
  <MyCar>
    <Position>
      <X>-1430.307</X>
      <Y>-3048.39331</Y>
      <Z>13.5477543</Z>
    </Position>
    <Rotation>
      <X>-0.003702942</X>
      <Y>0.00309176673</Y>
      <Z>89.96626</Z>
    </Rotation>
    <Handle>514</Handle>
    <Bounds>
      <Vector3>
        <X>-1427.74976</X>
        <Y>-3049.41626</Y>
        <Z>12.8200254</Z>
      </Vector3>
      <Vector3>
        <X>-1427.74854</X>
        <Y>-3047.37354</Y>
        <Z>12.8199158</Z>
      </Vector3>
      <Vector3>
        <X>-1432.86523</X>
        <Y>-3049.413</Y>
        <Z>12.8196945</Z>
      </Vector3>
      <Vector3>
        <X>-1427.74976</X>
        <Y>-3049.41626</Y>
        <Z>14.2759228</Z>
      </Vector3>
      <Vector3>
        <X>-1432.864</X>
        <Y>-3047.37061</Y>
        <Z>12.8195848</Z>
      </Vector3>
      <Vector3>
        <X>-1427.74854</X>
        <Y>-3047.37354</Y>
        <Z>14.2758131</Z>
      </Vector3>
      <Vector3>
        <X>-1432.86523</X>
        <Y>-3049.413</Y>
        <Z>14.2755919</Z>
      </Vector3>
      <Vector3>
        <X>-1432.864</X>
        <Y>-3047.37061</Y>
        <Z>14.2754822</Z>
      </Vector3>
    </Bounds>
    <CenterCamPosition>
      <X>0</X>
      <Y>0</Y>
    </CenterCamPosition>
    <ScreenBounds />
    <DistanceToCam>0</DistanceToCam>
    <Speed>10.6991186</Speed>
    <AccInput>0.111111127</AccInput>
    <RPM>0.426432073</RPM>
    <Gear>2</Gear>
    <SteeringAngle>0</SteeringAngle>
    <WheelSpeed>0</WheelSpeed>
    <CarType>Sports</CarType>
  </MyCar>
  <Peds />
  <Time>162548</Time>
  <LastFrameTime>0.01646874</LastFrameTime>
  <MyProperty>0</MyProperty>
  <Weather>ExtraSunny</Weather>
  <Steering>127</Steering>
  <Acc>141</Acc>
  <Brake>127</Brake>
  <DayTime>23:53:46</DayTime>
  <Position>
    <X>-1431.33093</X>
    <Y>-3048.39282</Y>
    <Z>14.4476957</Z>
  </Position>
  <Rotation>
    <X>-0.5039997</X>
    <Y>0.5029055</Y>
    <Z>89.9673843</Z>
  </Rotation>
</Screenshot>