<?xml version="1.0" encoding="utf-8"?>
<Screenshot xmlns:xsd="http://www.w3.org/2001/XMLSchema" xmlns:xsi="http://www.w3.org/2001/XMLSchema-instance">
  <Cars />
  <MyCar>
    <Position>
      <X>-1613.02612</X>
      <Y>-2732.89551</Y>
      <Z>13.5176373</Z>
    </Position>
    <Rotation>
      <X>1.75020087</X>
      <Y>0.0013508508</Y>
      <Z>-0.0146052614</Z>
    </Rotation>
    <Handle>514</Handle>
    <Bounds>
      <Vector3>
        <X>-1614.0481</X>
        <Y>-2735.42969</Y>
        <Z>12.7119293</Z>
      </Vector3>
      <Vector3>
        <X>-1612.00549</X>
        <Y>-2735.43018</Y>
        <Z>12.7118816</Z>
      </Vector3>
      <Vector3>
        <X>-1614.04688</X>
        <Y>-2730.31665</Y>
        <Z>12.8681669</Z>
      </Vector3>
      <Vector3>
        <X>-1614.0481</X>
        <Y>-2735.474</Y>
        <Z>14.1671476</Z>
      </Vector3>
      <Vector3>
        <X>-1612.00427</X>
        <Y>-2730.31714</Y>
        <Z>12.8681183</Z>
      </Vector3>
      <Vector3>
        <X>-1612.00549</X>
        <Y>-2735.47461</Y>
        <Z>14.1671</Z>
      </Vector3>
      <Vector3>
        <X>-1614.04688</X>
        <Y>-2730.361</Y>
        <Z>14.3233843</Z>
      </Vector3>
      <Vector3>
        <X>-1612.00427</X>
        <Y>-2730.36157</Y>
        <Z>14.3233366</Z>
      </Vector3>
    </Bounds>
    <CenterCamPosition>
      <X>0</X>
      <Y>0</Y>
    </CenterCamPosition>
    <ScreenBounds />
    <DistanceToCam>0</DistanceToCam>
    <Speed>5.57703257</Speed>
    <AccInput>0.2679739</AccInput>
    <RPM>0.351116031</RPM>
    <Gear>1</Gear>
    <SteeringAngle>0</SteeringAngle>
    <WheelSpeed>0</WheelSpeed>
    <CarType>Sports</CarType>
  </MyCar>
  <Peds />
  <Time>597102</Time>
  <LastFrameTime>0.0165779665</LastFrameTime>
  <MyProperty>0</MyProperty>
  <Weather>ExtraSunny</Weather>
  <Steering>127</Steering>
  <Acc>161</Acc>
  <Brake>127</Brake>
  <DayTime>03:30:39</DayTime>
  <Position>
    <X>-1613.02576</X>
    <Y>-2731.81616</Y>
    <Z>14.4539452</Z>
  </Position>
  <Rotation>
    <X>1.24791741</X>
    <Y>0.500793755</Y>
    <Z>-0.0115290061</Z>
  </Rotation>
</Screenshot>