<?xml version="1.0" encoding="utf-8"?>
<Screenshot xmlns:xsd="http://www.w3.org/2001/XMLSchema" xmlns:xsi="http://www.w3.org/2001/XMLSchema-instance">
  <Cars />
  <MyCar>
    <Position>
      <X>-1613.03223</X>
      <Y>-2711.729</Y>
      <Z>13.5030489</Z>
    </Position>
    <Rotation>
      <X>1.60803759</X>
      <Y>0.0258025117</Y>
      <Z>0.0617705472</Z>
    </Rotation>
    <Handle>514</Handle>
    <Bounds>
      <Vector3>
        <X>-1614.05127</X>
        <Y>-2714.2666</Y>
        <Z>12.7040682</Z>
      </Vector3>
      <Vector3>
        <X>-1612.00867</X>
        <Y>-2714.2644</Y>
        <Z>12.7031479</Z>
      </Vector3>
      <Vector3>
        <X>-1614.05664</X>
        <Y>-2709.153</Y>
        <Z>12.8476181</Z>
      </Vector3>
      <Vector3>
        <X>-1614.05054</X>
        <Y>-2714.30737</Y>
        <Z>14.1593924</Z>
      </Vector3>
      <Vector3>
        <X>-1612.014</X>
        <Y>-2709.151</Y>
        <Z>12.8466978</Z>
      </Vector3>
      <Vector3>
        <X>-1612.00793</X>
        <Y>-2714.30518</Y>
        <Z>14.1584721</Z>
      </Vector3>
      <Vector3>
        <X>-1614.05591</X>
        <Y>-2709.19385</Y>
        <Z>14.3029413</Z>
      </Vector3>
      <Vector3>
        <X>-1612.01331</X>
        <Y>-2709.19165</Y>
        <Z>14.302022</Z>
      </Vector3>
    </Bounds>
    <CenterCamPosition>
      <X>0</X>
      <Y>0</Y>
    </CenterCamPosition>
    <ScreenBounds />
    <DistanceToCam>0</DistanceToCam>
    <Speed>11.5731812</Speed>
    <AccInput>0.19477129</AccInput>
    <RPM>0.462140441</RPM>
    <Gear>2</Gear>
    <SteeringAngle>0</SteeringAngle>
    <WheelSpeed>0</WheelSpeed>
    <CarType>Sports</CarType>
  </MyCar>
  <Peds />
  <Time>599371</Time>
  <LastFrameTime>0.01625401</LastFrameTime>
  <MyProperty>0</MyProperty>
  <Weather>ExtraSunny</Weather>
  <Steering>127</Steering>
  <Acc>151</Acc>
  <Brake>127</Brake>
  <DayTime>03:31:47</DayTime>
  <Position>
    <X>-1613.03223</X>
    <Y>-2710.74268</Y>
    <Z>14.4364777</Z>
  </Position>
  <Rotation>
    <X>1.10857248</X>
    <Y>0.527794659</Y>
    <Z>0.07267681</Z>
  </Rotation>
</Screenshot>