<?xml version="1.0" encoding="utf-8"?>
<Screenshot xmlns:xsd="http://www.w3.org/2001/XMLSchema" xmlns:xsi="http://www.w3.org/2001/XMLSchema-instance">
  <Cars />
  <MyCar>
    <Position>
      <X>-685.542</X>
      <Y>-1925.8811</Y>
      <Z>36.1341171</Z>
    </Position>
    <Rotation>
      <X>0.2515937</X>
      <Y>-2.22457218</Y>
      <Z>150.220352</Z>
    </Rotation>
    <Handle>514</Handle>
    <Bounds>
      <Vector3>
        <X>-683.4124</X>
        <Y>-1924.15649</Y>
        <Z>35.3558578</Z>
      </Vector3>
      <Vector3>
        <X>-685.18396</X>
        <Y>-1923.14282</Y>
        <Z>35.4351463</Z>
      </Vector3>
      <Vector3>
        <X>-685.952332</X>
        <Y>-1928.59692</Y>
        <Z>35.3783073</Z>
      </Vector3>
      <Vector3>
        <X>-683.360168</X>
        <Y>-1924.17908</Y>
        <Z>36.8106461</Z>
      </Vector3>
      <Vector3>
        <X>-687.723938</X>
        <Y>-1927.58325</Y>
        <Z>35.4575958</Z>
      </Vector3>
      <Vector3>
        <X>-685.1318</X>
        <Y>-1923.16528</Y>
        <Z>36.8899345</Z>
      </Vector3>
      <Vector3>
        <X>-685.900146</X>
        <Y>-1928.61951</Y>
        <Z>36.83309</Z>
      </Vector3>
      <Vector3>
        <X>-687.6717</X>
        <Y>-1927.60571</Y>
        <Z>36.91238</Z>
      </Vector3>
    </Bounds>
    <CenterCamPosition>
      <X>0</X>
      <Y>0</Y>
    </CenterCamPosition>
    <ScreenBounds />
    <DistanceToCam>0</DistanceToCam>
    <Speed>16.4856319</Speed>
    <AccInput>0.200000048</AccInput>
    <RPM>0.65745</RPM>
    <Gear>2</Gear>
    <SteeringAngle>0.4076349</SteeringAngle>
    <WheelSpeed>0</WheelSpeed>
    <CarType>Sports</CarType>
  </MyCar>
  <Peds />
  <Time>312119</Time>
  <LastFrameTime>0.0338472873</LastFrameTime>
  <MyProperty>0</MyProperty>
  <Weather>ExtraSunny</Weather>
  <Steering>127</Steering>
  <Acc>152</Acc>
  <Brake>127</Brake>
  <DayTime>00:56:41</DayTime>
  <Position>
    <X>-685.83</X>
    <Y>-1926.4519</Y>
    <Z>37.03687</Z>
  </Position>
  <Rotation>
    <X>-0.26020664</X>
    <Y>-1.529357</Y>
    <Z>150.147964</Z>
  </Rotation>
</Screenshot>