<?xml version="1.0" encoding="utf-8"?>
<Screenshot xmlns:xsd="http://www.w3.org/2001/XMLSchema" xmlns:xsi="http://www.w3.org/2001/XMLSchema-instance">
  <Cars />
  <MyCar>
    <Position>
      <X>-693.2679</X>
      <Y>-1951.1936</Y>
      <Z>36.139576</Z>
    </Position>
    <Rotation>
      <X>0.2971482</X>
      <Y>-1.7985332</Y>
      <Z>177.452179</Z>
    </Rotation>
    <Handle>514</Handle>
    <Bounds>
      <Vector3>
        <X>-692.1578</X>
        <Y>-1948.68652</Y>
        <Z>35.366684</Z>
      </Vector3>
      <Vector3>
        <X>-694.197449</X>
        <Y>-1948.59583</Y>
        <Z>35.4307938</Z>
      </Vector3>
      <Vector3>
        <X>-692.3844</X>
        <Y>-1953.797</Y>
        <Z>35.3932037</Z>
      </Vector3>
      <Vector3>
        <X>-692.1118</X>
        <Y>-1948.681</Y>
        <Z>36.821846</Z>
      </Vector3>
      <Vector3>
        <X>-694.424</X>
        <Y>-1953.7063</Y>
        <Z>35.4573135</Z>
      </Vector3>
      <Vector3>
        <X>-694.1515</X>
        <Y>-1948.59033</Y>
        <Z>36.8859558</Z>
      </Vector3>
      <Vector3>
        <X>-692.3384</X>
        <Y>-1953.7915</Y>
        <Z>36.848362</Z>
      </Vector3>
      <Vector3>
        <X>-694.378052</X>
        <Y>-1953.70081</Y>
        <Z>36.91247</Z>
      </Vector3>
    </Bounds>
    <CenterCamPosition>
      <X>0</X>
      <Y>0</Y>
    </CenterCamPosition>
    <ScreenBounds />
    <DistanceToCam>0</DistanceToCam>
    <Speed>17.26351</Speed>
    <AccInput>0.2052288</AccInput>
    <RPM>0.688454032</RPM>
    <Gear>2</Gear>
    <SteeringAngle>8.836267</SteeringAngle>
    <WheelSpeed>0</WheelSpeed>
    <CarType>Sports</CarType>
  </MyCar>
  <Peds />
  <Time>313702</Time>
  <LastFrameTime>0.0334463753</LastFrameTime>
  <MyProperty>0</MyProperty>
  <Weather>ExtraSunny</Weather>
  <Steering>127</Steering>
  <Acc>153</Acc>
  <Brake>127</Brake>
  <DayTime>00:57:28</DayTime>
  <Position>
    <X>-693.280457</X>
    <Y>-1951.81128</Y>
    <Z>37.0435028</Z>
  </Position>
  <Rotation>
    <X>-0.157024622</X>
    <Y>-1.37466717</Y>
    <Z>176.643524</Z>
  </Rotation>
</Screenshot>