<?xml version="1.0" encoding="utf-8"?>
<Screenshot xmlns:xsd="http://www.w3.org/2001/XMLSchema" xmlns:xsi="http://www.w3.org/2001/XMLSchema-instance">
  <Cars />
  <MyCar>
    <Position>
      <X>-1342.19</X>
      <Y>-3040.32</Y>
      <Z>13.5548449</Z>
    </Position>
    <Rotation>
      <X>-0.132962629</X>
      <Y>5.30340221E-05</Y>
      <Z>56.0776176</Z>
    </Rotation>
    <Handle>514</Handle>
    <Bounds>
      <Vector3>
        <X>-1340.636</X>
        <Y>-3042.596</Y>
        <Z>12.8328342</Z>
      </Vector3>
      <Vector3>
        <X>-1339.49609</X>
        <Y>-3040.90112</Y>
        <Z>12.8328323</Z>
      </Vector3>
      <Vector3>
        <X>-1344.88086</X>
        <Y>-3039.74121</Y>
        <Z>12.8209629</Z>
      </Vector3>
      <Vector3>
        <X>-1340.63879</X>
        <Y>-3042.594</Y>
        <Z>14.2887278</Z>
      </Vector3>
      <Vector3>
        <X>-1343.741</X>
        <Y>-3038.04639</Y>
        <Z>12.820961</Z>
      </Vector3>
      <Vector3>
        <X>-1339.4989</X>
        <Y>-3040.89917</Y>
        <Z>14.2887259</Z>
      </Vector3>
      <Vector3>
        <X>-1344.88367</X>
        <Y>-3039.73926</Y>
        <Z>14.2768564</Z>
      </Vector3>
      <Vector3>
        <X>-1343.74365</X>
        <Y>-3038.04443</Y>
        <Z>14.2768545</Z>
      </Vector3>
    </Bounds>
    <CenterCamPosition>
      <X>0</X>
      <Y>0</Y>
    </CenterCamPosition>
    <ScreenBounds />
    <DistanceToCam>0</DistanceToCam>
    <Speed>7.671657</Speed>
    <AccInput>0</AccInput>
    <RPM>0.5353939</RPM>
    <Gear>1</Gear>
    <SteeringAngle>8.438069E-37</SteeringAngle>
    <WheelSpeed>0</WheelSpeed>
    <CarType>Sports</CarType>
  </MyCar>
  <Peds />
  <Time>111701</Time>
  <LastFrameTime>0.0340852924</LastFrameTime>
  <MyProperty>0</MyProperty>
  <Weather>ExtraSunny</Weather>
  <Steering>127</Steering>
  <Acc>127</Acc>
  <Brake>127</Brake>
  <DayTime>23:27:57</DayTime>
  <Position>
    <X>-1342.96924</X>
    <Y>-3039.796</Y>
    <Z>14.4526148</Z>
  </Position>
  <Rotation>
    <X>-0.598842144</X>
    <Y>0.500247955</Y>
    <Z>56.07762</Z>
  </Rotation>
</Screenshot>