<?xml version="1.0" encoding="utf-8"?>
<Screenshot xmlns:xsd="http://www.w3.org/2001/XMLSchema" xmlns:xsi="http://www.w3.org/2001/XMLSchema-instance">
  <Cars />
  <MyCar>
    <Position>
      <X>-1365.43384</X>
      <Y>-3024.687</Y>
      <Z>13.54874</Z>
    </Position>
    <Rotation>
      <X>-0.008542459</X>
      <Y>0.0120953685</Y>
      <Z>56.0787926</Z>
    </Rotation>
    <Handle>514</Handle>
    <Bounds>
      <Vector3>
        <X>-1363.88123</X>
        <Y>-3026.96216</Y>
        <Z>12.8213882</Z>
      </Vector3>
      <Vector3>
        <X>-1362.74146</X>
        <Y>-3025.267</Y>
        <Z>12.8209572</Z>
      </Vector3>
      <Vector3>
        <X>-1368.1261</X>
        <Y>-3024.10742</Y>
        <Z>12.8206253</Z>
      </Vector3>
      <Vector3>
        <X>-1363.88135</X>
        <Y>-3026.96167</Y>
        <Z>14.2772856</Z>
      </Vector3>
      <Vector3>
        <X>-1366.98621</X>
        <Y>-3022.4126</Y>
        <Z>12.8201942</Z>
      </Vector3>
      <Vector3>
        <X>-1362.74146</X>
        <Y>-3025.26685</Y>
        <Z>14.2768545</Z>
      </Vector3>
      <Vector3>
        <X>-1368.1261</X>
        <Y>-3024.10718</Y>
        <Z>14.2765226</Z>
      </Vector3>
      <Vector3>
        <X>-1366.98621</X>
        <Y>-3022.412</Y>
        <Z>14.2760916</Z>
      </Vector3>
    </Bounds>
    <CenterCamPosition>
      <X>0</X>
      <Y>0</Y>
    </CenterCamPosition>
    <ScreenBounds />
    <DistanceToCam>0</DistanceToCam>
    <Speed>10.2853155</Speed>
    <AccInput>0.283660173</AccInput>
    <RPM>0.409830749</RPM>
    <Gear>2</Gear>
    <SteeringAngle>0</SteeringAngle>
    <WheelSpeed>0</WheelSpeed>
    <CarType>Sports</CarType>
  </MyCar>
  <Peds />
  <Time>115763</Time>
  <LastFrameTime>0.01616123</LastFrameTime>
  <MyProperty>0</MyProperty>
  <Weather>ExtraSunny</Weather>
  <Steering>127</Steering>
  <Acc>163</Acc>
  <Brake>127</Brake>
  <DayTime>23:29:58</DayTime>
  <Position>
    <X>-1366.29175</X>
    <Y>-3024.10986</Y>
    <Z>14.4485235</Z>
  </Position>
  <Rotation>
    <X>-0.5117882</X>
    <Y>0.5120853</Y>
    <Z>56.07877</Z>
  </Rotation>
</Screenshot>